adata_query/__init__.py
adata_query/__version__.py
adata_query/_logging.py
adata_query/_core/__init__.py
adata_query/_core/_fetcher.py
adata_query/_core/_formatter.py
adata_query/_core/_locator.py
adata_query-0.1.0.dist-info/licenses/LICENSE
adata_query-0.1.0.dist-info/METADATA
adata_query-0.1.0.dist-info/WHEEL
adata_query-0.1.0.dist-info/top_level.txt
adata_query-0.1.0.dist-info/RECORD
