Metadata-Version: 2.4
Name: adata_query
Version: 0.1.0
Summary: Fetch and format data matrices from AnnData.
Home-page: https://github.com/mvinyard/AnnDataQuery
Author: Michael E. Vinyard
Author-email: mvinyard.ai@gmail.com
License: MIT
Classifier: Development Status :: 2 - Pre-Alpha
Classifier: Programming Language :: Python :: 3.9
Classifier: Intended Audience :: Science/Research
Classifier: Topic :: Scientific/Engineering :: Bio-Informatics
Requires-Python: >3.9.0
License-File: LICENSE
Requires-Dist: anndata>=0.11
Requires-Dist: torch>=2.5
Requires-Dist: autodevice>=0.0.2
Requires-Dist: ABCParse>=0.1.4
Dynamic: author
Dynamic: author-email
Dynamic: classifier
Dynamic: description
Dynamic: description-content-type
Dynamic: home-page
Dynamic: license
Dynamic: license-file
Dynamic: requires-dist
Dynamic: requires-python
Dynamic: summary
